conda_store_server/__init__.py
conda_store_server/api.py
conda_store_server/conda_store.py
conda_store_server/conda_store_config.py
conda_store_server/exception.py
conda_store_server/registry.py
conda_store_server/storage.py
conda_store_server/_internal/__init__.py
conda_store_server/_internal/alembic.ini
conda_store_server/_internal/conda_utils.py
conda_store_server/_internal/dbutil.py
conda_store_server/_internal/environment.py
conda_store_server/_internal/orm.py
conda_store_server/_internal/schema.py
conda_store_server/_internal/settings.py
conda_store_server/_internal/utils.py
conda_store_server/_internal/action/__init__.py
conda_store_server/_internal/action/add_conda_prefix_packages.py
conda_store_server/_internal/action/add_lockfile_packages.py
conda_store_server/_internal/action/base.py
conda_store_server/_internal/action/download_packages.py
conda_store_server/_internal/action/generate_conda_export.py
conda_store_server/_internal/action/generate_conda_pack.py
conda_store_server/_internal/action/generate_constructor_installer.py
conda_store_server/_internal/action/generate_lockfile.py
conda_store_server/_internal/action/get_conda_prefix_stats.py
conda_store_server/_internal/action/install_lockfile.py
conda_store_server/_internal/action/install_specification.py
conda_store_server/_internal/action/remove_conda_prefix.py
conda_store_server/_internal/action/set_conda_prefix_permissions.py
conda_store_server/_internal/action/utils.py
conda_store_server/_internal/alembic/README
conda_store_server/_internal/alembic/env.py
conda_store_server/_internal/alembic/script.py.mako
conda_store_server/_internal/alembic/versions/03c839888c82_add_canceled_status.py
conda_store_server/_internal/alembic/versions/0f7e23ff24ee_add_worker.py
conda_store_server/_internal/alembic/versions/16f65805dc8f_split_conda_package_into_conda_package_.py
conda_store_server/_internal/alembic/versions/30b37e725c32_add_build_key_version.py
conda_store_server-2025.2.1.dist-info/METADATA
conda_store_server-2025.2.1.dist-info/WHEEL
conda_store_server-2025.2.1.dist-info/entry_points.txt
conda_store_server-2025.2.1.dist-info/licenses/LICENSE
conda_store_server-2025.2.1.dist-info/RECORD
